NgPep/__init__.py
NgPep/area.py
NgPep-0.0.1.dist-info/METADATA
NgPep-0.0.1.dist-info/WHEEL
NgPep-0.0.1.dist-info/top_level.txt
NgPep-0.0.1.dist-info/RECORD
