Metadata-Version: 2.1
Name: NgPep
Version: 0.0.1
Summary: area of different shapes
Author: Peter Ojo
Author-email: peterojo2dev@gmail.com
